signal_correction/__init__.py
signal_correction/signal_correction.py
signal_correction-1.0a8.dist-info/METADATA
signal_correction-1.0a8.dist-info/WHEEL
signal_correction-1.0a8.dist-info/RECORD
