Metadata-Version: 2.4
Name: signal_correction
Version: 1.0a8
Summary: Signal correction module for Ariel Data Challenge 2025.
Project-URL: Homepage, https://github.com/gperdrizet/ariel-data-challenge
Project-URL: Issues, https://github.com/gperdrizet/ariel-data-challenge/issues
Author-email: George Perdrizet <george@perdrizet.org>
License-Expression: GPL-3.0-or-later
Classifier: Operating System :: OS Independent
Classifier: Programming Language :: Python :: 3
Requires-Python: >=3.8
Requires-Dist: astropy
Requires-Dist: numpy
